multipagetiff/__init__.py
multipagetiff/config.py
multipagetiff/image_tools/__init__.py
multipagetiff/image_tools/image_tools.py
multipagetiff/io/__init__.py
multipagetiff/io/io.py
multipagetiff/plot/__init__.py
multipagetiff/plot/plot.py
multipagetiff/stack/__init__.py
multipagetiff/stack/stack.py
multipagetiff/stacktools/__init__.py
multipagetiff/stacktools/stacktools.py
multipagetiff/transform/__init__.py
multipagetiff/transform/affine3d.py
multipagetiff-3.0.9.dist-info/LICENSE.TXT
multipagetiff-3.0.9.dist-info/METADATA
multipagetiff-3.0.9.dist-info/WHEEL
multipagetiff-3.0.9.dist-info/top_level.txt
multipagetiff-3.0.9.dist-info/RECORD
