Metadata-Version: 2.1
Name: multipagetiff
Version: 3.0.9
Summary: open multipage tiff stacks and create z-projections
Home-page: https://github.com/mpascucci/multipagetiff
Author: Marco Pascucci
Author-email: marpas.paris@gmail.com
Classifier: Programming Language :: Python
Classifier: License :: OSI Approved :: GNU General Public License v2 (GPLv2)
Classifier: Operating System :: OS Independent
License-File: LICENSE.TXT
Requires-Dist: numpy
Requires-Dist: matplotlib
Requires-Dist: tqdm
Requires-Dist: scipy
